gradio_model3dgscamera/__init__.py
gradio_model3dgscamera/model3dgscamera.py
gradio_model3dgscamera/model3dgscamera.pyi
gradio_model3dgscamera/templates/component/Canvas3DGSCamera-CJprx23B.js
gradio_model3dgscamera/templates/component/index.js
gradio_model3dgscamera/templates/component/style.css
gradio_model3dgscamera/templates/example/index.js
gradio_model3dgscamera/templates/example/style.css
gradio_model3dgscamera-0.0.3.dist-info/METADATA
gradio_model3dgscamera-0.0.3.dist-info/WHEEL
gradio_model3dgscamera-0.0.3.dist-info/licenses/LICENSE
gradio_model3dgscamera-0.0.3.dist-info/RECORD
