Metadata-Version: 2.3
Name: gradio_model3dgscamera
Version: 0.0.3
Summary: 3DGS viewer with camera control
Project-URL: repository, https://github.com/hellnear/gradio-model3dgscamera
Author-email: YOUR NAME <YOUREMAIL@domain.com>
License-Expression: MIT
License-File: LICENSE
Keywords: gradio-custom-component,gradio-template-Model3D
Classifier: Development Status :: 3 - Alpha
Classifier: Operating System :: OS Independent
Classifier: Programming Language :: Python :: 3
Classifier: Programming Language :: Python :: 3 :: Only
Classifier: Programming Language :: Python :: 3.8
Classifier: Programming Language :: Python :: 3.9
Classifier: Programming Language :: Python :: 3.10
Classifier: Programming Language :: Python :: 3.11
Classifier: Topic :: Scientific/Engineering
Classifier: Topic :: Scientific/Engineering :: Artificial Intelligence
Classifier: Topic :: Scientific/Engineering :: Visualization
Requires-Python: >=3.8
Requires-Dist: gradio<5.0,>=4.0
Provides-Extra: dev
Requires-Dist: build; extra == 'dev'
Requires-Dist: twine; extra == 'dev'
